{"msg":{"list":[{"title":null,"userName":"林于丰","submitUpdateTime":"2017-01-16","headImage":"http://wx.qlogo.cn/mmopen/wbKdib81ny6icvAJKfaPXrYVpc64VKYR3pcRQ6uiaXVZvPBEGwfTnp5t7b8qOZNmuJthzjTr4flT8pzXUuBEiaYgUg/0","content":"1、素材\n有关企业税收负担重还是不重的争论，终于有了明确的官方结论。1月16日，新华社播发了财政部前部长、全国社保基金理事会理事长楼继伟的观点：中国的税负不重。\n\n楼继伟表示，美国企业所得税率为35%，中国税率是25%。从国际比较来看，无论哪个口径，中国宏观税负都低于世界平均水平。楼继伟指出：“比较税负，关键看宏观税负，即总收入与名义GDP的比值。如果不包括国有土地使用权出让收入，2014、2015年我国宏观税负均为29%左右，如果计入国有土地出让净收益，宏观税负分别为30.2%和29.8%。”\n\n而此前，世行报告称2016年所有国家（地区）平均总税率为40.6%，中国总税率为68％，位列全球第12位。\n\n2、评：对于中国税负额数据悬殊的原因是双方的统计方法不同。\n\n负责协调纳税报告的乔安娜·纳斯尔在给新华社记者的邮件中说，报告团队以“假定情形”为基础，在主要城市中设定一两家中等规模标准企业，综合销售利润率、员工结构和工资水平、固定资产处置行为等因素进行测算。简言之，总税率等于企业纳税额加强制性派款等支出除以商业利润，其中纳税额不包括由个人负担的个人所得税和不影响利润的增值税，强制性派款在中国指五险一金，商业利润指企业缴纳所有税款前的净利润，并非企业财务上的所得税前利润。\n\n而楼继伟代表的官方算法并没有加入土地出让金、强制性派款以及企业承担的各种费用。以2015年的数据为例，如果把企业实际应缴税费加起来，其在利润中的占比高达68%左右，从上市公司年报来看，这一税率普遍在50%以上，部分行业甚至高达80%。\n\n楼继伟所代表的权威认为世行的统计方法没有意义，是可以质疑的权威观点，而世行报告代表的权威，是可信的权威观点。\n\n一言以敝之，某一权威的观点可靠或不可靠，需要考虑所谓的权威屁股坐在什么位置，屁股决定脑袋。\n\n资料来源：《“中国总税率为68%”说法靠谱吗 楼继伟：意义不大》新华社 1月16日","voteCount":0,"commentCount":1,"submitId":117,"type":11,"voteStatus":0,"publishTime":1484566004000,"priority":0,"perfect":null,"problemId":null,"authorType":null,"isMine":null,"labelList":null,"picList":[]}],"highlightList":[],"end":true},"code":200}
